sparseypy/__init__.py
sparseypy/access_objects/__init__.py
sparseypy/access_objects/datasets/__init__.py
sparseypy/access_objects/datasets/built_in_dataset.py
sparseypy/access_objects/datasets/dataset.py
sparseypy/access_objects/datasets/dataset_factory.py
sparseypy/access_objects/datasets/image_dataset.py
sparseypy/access_objects/datasets/in_memory_dataset.py
sparseypy/access_objects/datasets/preprocessed_dataset.py
sparseypy/access_objects/datasets/sparsey_dataset.py
sparseypy/access_objects/hpo_runs/__init__.py
sparseypy/access_objects/hpo_runs/hpo_run.py
sparseypy/access_objects/models/model.py
sparseypy/access_objects/models/model_builder.py
sparseypy/access_objects/plot/build_plot.py
sparseypy/access_objects/preprocessing_stack/preprocessing_stack.py
sparseypy/access_objects/training_recipes/training_recipe.py
sparseypy/access_objects/training_recipes/training_recipe_builder.py
sparseypy/cli/__init__.py
sparseypy/cli/config_validation/__init__.py
sparseypy/cli/config_validation/schema_factory.py
sparseypy/cli/config_validation/validate_config.py
sparseypy/cli/config_validation/saved_schemas/__init__.py
sparseypy/cli/config_validation/saved_schemas/abs_schema.py
sparseypy/cli/config_validation/saved_schemas/schema_utils.py
sparseypy/cli/config_validation/saved_schemas/dataset/__init__.py
sparseypy/cli/config_validation/saved_schemas/dataset/built_in.py
sparseypy/cli/config_validation/saved_schemas/dataset/image.py
sparseypy/cli/config_validation/saved_schemas/dataset/sparsey.py
sparseypy/cli/config_validation/saved_schemas/db_adapter/__init__.py
sparseypy/cli/config_validation/saved_schemas/db_adapter/firestore.py
sparseypy/cli/config_validation/saved_schemas/hpo/__init__.py
sparseypy/cli/config_validation/saved_schemas/hpo/default.py
sparseypy/cli/config_validation/saved_schemas/metric/__init__.py
sparseypy/cli/config_validation/saved_schemas/metric/basis_average.py
sparseypy/cli/config_validation/saved_schemas/metric/basis_set_size.py
sparseypy-0.0.5.dist-info/METADATA
sparseypy-0.0.5.dist-info/WHEEL
sparseypy-0.0.5.dist-info/entry_points.txt
sparseypy-0.0.5.dist-info/licenses/LICENSE
sparseypy-0.0.5.dist-info/RECORD
